MANIFEST.in
README.rst
setup.py
collective/__init__.py
collective.flexitopic.egg-info/PKG-INFO
collective.flexitopic.egg-info/SOURCES.txt
collective.flexitopic.egg-info/dependency_links.txt
collective.flexitopic.egg-info/entry_points.txt
collective.flexitopic.egg-info/namespace_packages.txt
collective.flexitopic.egg-info/not-zip-safe
collective.flexitopic.egg-info/requires.txt
collective.flexitopic.egg-info/top_level.txt
collective/flexitopic/README.txt
collective/flexitopic/__init__.py
collective/flexitopic/configure.zcml
collective/flexitopic/i18n.sh
collective/flexitopic/interfaces.py
collective/flexitopic/setuphandlers.py
collective/flexitopic/tests.py
collective/flexitopic/browser/__init__.py
collective/flexitopic/browser/configure.zcml
collective/flexitopic/browser/controlpanel.py
collective/flexitopic/browser/flexijsonview.py
collective/flexitopic/browser/flexitopicview.py
collective/flexitopic/browser/interfaces.py
collective/flexitopic/browser/utils.py
collective/flexitopic/browser/viewlets.py
collective/flexitopic/browser/templates/about_collection_viewlet.pt
collective/flexitopic/browser/templates/about_viewlet.pt
collective/flexitopic/browser/templates/flexicollectionview.pt
collective/flexitopic/browser/templates/flexitopicview.pt
collective/flexitopic/browser/templates/jstemplate.pt
collective/flexitopic/browser/templates/resulttable.pt
collective/flexitopic/browser/templates/searchform.pt
collective/flexitopic/browser/templates/subtopic_viewlet.pt
collective/flexitopic/browser/templates/table.pt
collective/flexitopic/locales/collective.flexitopic.pot
collective/flexitopic/locales/en/LC_MESSAGES/README.txt
collective/flexitopic/locales/en/LC_MESSAGES/collective.flexitopic.po
collective/flexitopic/locales/fr/LC_MESSAGES/collective.flexitopic.po
collective/flexitopic/locales/it/LC_MESSAGES/collective.flexitopic.po
collective/flexitopic/portlets/__init__.py
collective/flexitopic/portlets/configure.zcml
collective/flexitopic/portlets/flexitopicportlet.pt
collective/flexitopic/portlets/flexitopicportlet.py
collective/flexitopic/portlets/interfaces.py
collective/flexitopic/portlets/viewlets.py
collective/flexitopic/profiles/default/browserlayer.xml
collective/flexitopic/profiles/default/controlpanel.xml
collective/flexitopic/profiles/default/cssregistry.xml
collective/flexitopic/profiles/default/jsregistry.xml
