Metadata-Version: 1.1
Name: collective.flexitopic
Version: 0.7.1
Summary: Searchable Collections with Flexigrid
Home-page: https://github.com/collective/collective.flexitopic
Author: Christian Ledermann
Author-email: christian.ledermann@gmail.com
License: GPL
Platform: UNKNOWN
Classifier: Framework :: Plone
Classifier: Framework :: Plone :: 4.0
Classifier: Framework :: Plone :: 4.1
Classifier: Framework :: Plone :: 4.2
Classifier: Framework :: Plone :: 4.3
Classifier: Programming Language :: Python
Classifier: Development Status :: 5 - Production/Stable
Classifier: License :: OSI Approved :: GNU General Public License (GPL)
